<?xml version="1.0" encoding="utf-8"?>

<Items>
  <!-- Generic notesheet
       Simply copy code from this comment and enter values in your notesheet file for soundtrack addition.
       Custom soundtrack indentifier numbers begin from 101 in order to avoid possible conflicts with default soundtracks.
       Before reserving a number range, make sure that it isn't taken by someone else.
  <Item name="Note Sheet ####" identifier="notesheet###" category="Misc" Tags="smallitem,papers,notesheet,loop" canbepicked="true" description="Band Name - Song Name" cargocontaineridentifier="metalcrate" scale="1.0">
    <InventoryIcon texture="Mods/BaroTech Expansion - Unstable/InventoryIconAtlas.png" sourcerect="448,0,64,64" />
    <Sprite texture="Mods/BaroTech Expansion - Unstable/Papers/DocumentSprites.png" sourcerect="21,0,21,32" depth="0.55" origin="0.5,0.5" />
    <Fabricate suitablefabricators="printer" requiredtime="14">
       <RequiredItem identifier="paper" />
    </Fabricate>
    <Body width="21" height="32" density="10" />
    <Holdable canBeCombined="true" slots="Any,RightHand,LeftHand" handle1="0,0" msg="ItemMsgPickUpSelect">
      <sound file="Mods/mod_name_here/file_name_here.ogg" type="OnUse"  volume="2.0" range="2000" loop="true" />
    </Holdable>
  </Item>
  -->
</Items>